{
  "Container": {
    "Type": "Choice",
    "Containers": [
      {
        "Type": "Single",
        "Weight": 100,
        "Item": {
          "ItemId": "Weapon_Battleaxe_Adamantite"
        }
      },
      {
        "Type": "Single",
        "Weight": 100,
        "Item": {
          "ItemId": "Weapon_Battleaxe_Cobalt"
        }
      },
      {
        "Type": "Single",
        "Weight": 100,
        "Item": {
          "ItemId": "Weapon_Battleaxe_Copper"
        }
      },
      {
        "Type": "Single",
        "Weight": 100,
        "Item": {
          "ItemId": "Weapon_Battleaxe_Crude"
        }
      },
      {
        "Type": "Single",
        "Weight": 100,
        "Item": {
          "ItemId": "Weapon_Battleaxe_Doomed"
        }
      },
      {
        "Type": "Single",
        "Weight": 100,
        "Item": {
          "ItemId": "Weapon_Battleaxe_Iron"
        }
      },
      {
        "Type": "Single",
        "Weight": 100,
        "Item": {
          "ItemId": "Weapon_Battleaxe_Mithril"
        }
      },
      {
        "Type": "Single",
        "Weight": 100,
        "Item": {
          "ItemId": "Weapon_Battleaxe_Onyxium"
        }
      },
      {
        "Type": "Single",
        "Weight": 100,
        "Item": {
          "ItemId": "Weapon_Battleaxe_Scarab"
        }
      },
      {
        "Type": "Single",
        "Weight": 100,
        "Item": {
          "ItemId": "Weapon_Battleaxe_Scythe_Void"
        }
      },
      {
        "Type": "Single",
        "Weight": 100,
        "Item": {
          "ItemId": "Weapon_Battleaxe_Steel_Rusty"
        }
      },
      {
        "Type": "Single",
        "Weight": 100,
        "Item": {
          "ItemId": "Weapon_Battleaxe_Stone_Trork"
        }
      },
      {
        "Type": "Single",
        "Weight": 100,
        "Item": {
          "ItemId": "Weapon_Battleaxe_Thorium"
        }
      },
      {
        "Type": "Single",
        "Weight": 100,
        "Item": {
          "ItemId": "Weapon_Battleaxe_Tribal"
        }
      },
      {
        "Type": "Single",
        "Weight": 100,
        "Item": {
          "ItemId": "Weapon_Battleaxe_Wood_Fence"
        }
      },
      {
        "Type": "Single",
        "Weight": 100,
        "Item": {
          "ItemId": "Weapon_Daggers_Adamantite_Saurian"
        }
      },
      {
        "Type": "Single",
        "Weight": 100,
        "Item": {
          "ItemId": "Weapon_Daggers_Adamantite"
        }
      },
      {
        "Type": "Single",
        "Weight": 100,
        "Item": {
          "ItemId": "Weapon_Daggers_Bone"
        }
      },
      {
        "Type": "Single",
        "Weight": 100,
        "Item": {
          "ItemId": "Weapon_Daggers_Bronze_Ancient"
        }
      },
      {
        "Type": "Single",
        "Weight": 100,
        "Item": {
          "ItemId": "Weapon_Daggers_Bronze"
        }
      },
      {
        "Type": "Single",
        "Weight": 100,
        "Item": {
          "ItemId": "Weapon_Daggers_Claw_Bone"
        }
      },
      {
        "Type": "Single",
        "Weight": 100,
        "Item": {
          "ItemId": "Weapon_Daggers_Cobalt"
        }
      },
      {
        "Type": "Single",
        "Weight": 100,
        "Item": {
          "ItemId": "Weapon_Daggers_Copper"
        }
      },
      {
        "Type": "Single",
        "Weight": 100,
        "Item": {
          "ItemId": "Weapon_Daggers_Crude"
        }
      },
      {
        "Type": "Single",
        "Weight": 100,
        "Item": {
          "ItemId": "Weapon_Daggers_Doomed"
        }
      },
      {
        "Type": "Single",
        "Weight": 100,
        "Item": {
          "ItemId": "Weapon_Daggers_Fang_Doomed"
        }
      },
      {
        "Type": "Single",
        "Weight": 100,
        "Item": {
          "ItemId": "Weapon_Daggers_Iron"
        }
      },
      {
        "Type": "Single",
        "Weight": 100,
        "Item": {
          "ItemId": "Weapon_Daggers_Mithril"
        }
      },
      {
        "Type": "Single",
        "Weight": 100,
        "Item": {
          "ItemId": "Weapon_Daggers_Onyxium"
        }
      },
      {
        "Type": "Single",
        "Weight": 100,
        "Item": {
          "ItemId": "Weapon_Daggers_Stone_Trork"
        }
      },
      {
        "Type": "Single",
        "Weight": 100,
        "Item": {
          "ItemId": "Weapon_Daggers_Thorium"
        }
      },
      {
        "Type": "Single",
        "Weight": 100,
        "Item": {
          "ItemId": "Weapon_Kunai"
        }
      },
      {
        "Type": "Single",
        "Weight": 100,
        "Item": {
          "ItemId": "Weapon_Longsword_Iron"
        }
      },
      {
        "Type": "Single",
        "Weight": 100,
        "Item": {
          "ItemId": "Weapon_Longsword_Adamantite"
        }
      },
      {
        "Type": "Single",
        "Weight": 100,
        "Item": {
          "ItemId": "Weapon_Longsword_Cobalt"
        }
      },
      {
        "Type": "Single",
        "Weight": 100,
        "Item": {
          "ItemId": "Weapon_Longsword_Flame"
        }
      },
      {
        "Type": "Single",
        "Weight": 100,
        "Item": {
          "ItemId": "Weapon_Longsword_Spectral"
        }
      },
      {
        "Type": "Single",
        "Weight": 100,
        "Item": {
          "ItemId": "Weapon_Sword_Frost"
        }
      },
      {
        "Type": "Single",
        "Weight": 100,
        "Item": {
          "ItemId": "Weapon_Sword_Silversteel"
        }
      },
      {
        "Type": "Single",
        "Weight": 100,
        "Item": {
          "ItemId": "Weapon_Sword_Runic"
        }
      },
      {
        "Type": "Single",
        "Weight": 100,
        "Item": {
          "ItemId": "Weapon_Crossbow_Ancient_Steel"
        }
      },
      {
        "Type": "Single",
        "Weight": 100,
        "Item": {
          "ItemId": "Weapon_Crossbow_Iron"
        }
      }
    ],
    "RollsMin": 1,
    "RollsMax": 2
  }
}
